max_num/__init__.py
max_num/max.py
max_num/test.py
max_num-0.0.3.dist-info/LICENSE
max_num-0.0.3.dist-info/METADATA
max_num-0.0.3.dist-info/WHEEL
max_num-0.0.3.dist-info/top_level.txt
max_num-0.0.3.dist-info/RECORD
