Metadata-Version: 2.1
Name: max-num
Version: 0.0.3
Summary: check max_number of arguments,list and dictionary
Author-email: Esharat Mia <esharat1992@gmail.com>
Project-URL: Homepage, https://github.com/esharat1992/max_num
Project-URL: Bug Tracker, https://github.com/esharat1992/max_num/issues
Classifier: Programming Language :: Python :: 3
Classifier: License :: OSI Approved :: GNU General Public License (GPL)
Classifier: Operating System :: OS Independent
Requires-Python: >=3.7
License-File: LICENSE
